crypto_candlesticks/__init__.py
crypto_candlesticks/database.py
crypto_candlesticks/exchanges/__init__.py
crypto_candlesticks/exchanges/bitfinex.py
crypto_candlesticks/get_data.py
crypto_candlesticks/main.py
crypto_candlesticks/symbols/__init__.py
crypto_candlesticks/symbols/quote_currencies.py
crypto_candlesticks/symbols/time_intervals.py
crypto_candlesticks/text_console.py
crypto_candlesticks-0.2.1.dist-info/entry_points.txt
crypto_candlesticks-0.2.1.dist-info/LICENSE
crypto_candlesticks-0.2.1.dist-info/WHEEL
crypto_candlesticks-0.2.1.dist-info/METADATA
crypto_candlesticks-0.2.1.dist-info/RECORD
