Metadata-Version: 2.1
Name: crypto-candlesticks
Version: 0.2.1
Summary: Download candlestick data fast & easy for analysis
Home-page: https://crypto-candlesticks.readthedocs.io/en/latest/
License: GPL-3.0-or-later
Keywords: cryptocurrency,candlesticks,download,data,ohlc
Author: Pedro Torres
Author-email: corfucinas@protonmail.com
Requires-Python: >=3.8,<4.0
Classifier: Intended Audience :: Developers
Classifier: Intended Audience :: Education
Classifier: Intended Audience :: End Users/Desktop
Classifier: Intended Audience :: Financial and Insurance Industry
Classifier: Intended Audience :: Science/Research
Classifier: License :: OSI Approved :: GNU General Public License v3 or later (GPLv3+)
Classifier: Operating System :: OS Independent
Classifier: Programming Language :: Python :: 3
Classifier: Programming Language :: Python :: 3.10
Classifier: Programming Language :: Python :: 3.8
Classifier: Programming Language :: Python :: 3.9
Classifier: Topic :: Software Development :: Libraries :: Python Modules
Classifier: Topic :: System :: Software Distribution
Classifier: Topic :: Terminals
Classifier: Topic :: Utilities
Requires-Dist: click (>=8.0.3,<9.0.0)
Requires-Dist: pandas (>=1.0.5,<2.0.0)
Requires-Dist: requests (>=2.24.0,<3.0.0)
Requires-Dist: retry (>=0.9.2,<0.10.0)
Requires-Dist: rich (>=11.0.0,<12.0.0)
Project-URL: Repository, https://github.com/Corfucinas/crypto-candlesticks
Project-URL: issues, https://github.com/Corfucinas/crypto-candlesticks/issues/new/choose
